dash_obj_in_3dmesh/__init__.py
dash_obj_in_3dmesh/_config.py
dash_obj_in_3dmesh/app.py
dash_obj_in_3dmesh/geometry_tools.py
dash_obj_in_3dmesh/mesh_tools.py
dash_obj_in_3dmesh/wav_obj.py
dash_obj_in_3dmesh-0.4.0.dist-info/LICENSE.md
dash_obj_in_3dmesh-0.4.0.dist-info/METADATA
dash_obj_in_3dmesh-0.4.0.dist-info/WHEEL
dash_obj_in_3dmesh-0.4.0.dist-info/top_level.txt
dash_obj_in_3dmesh-0.4.0.dist-info/RECORD
