Metadata-Version: 2.1
Name: dash-obj-in-3dmesh
Version: 0.4.0
Summary: Some tools for getting Wavefront OBJ files into a Plotly Dash 3dmesh graph
Home-page: UNKNOWN
Author: Jon Robinson
Author-email: jonrobinson1980@gmail.com
License: CC Attribution 4.0 International
Platform: UNKNOWN
Classifier: Framework :: Dash
Requires-Python: >=3.5
Requires-Dist: numpy
Requires-Dist: dash
